dotfiles/__init__.py
dotfiles/__main__.py
dotfiles/metafiles/.editorconfig
dotfiles/metafiles/.gitattributes
dotfiles/metafiles/.gitignore
dotfiles/metafiles/.markdownlint.json
dotfiles/metafiles/.prospector.yml
dotfiles/metafiles/.pylintrc
dotfiles/metafiles/.setup.cfg
dotfiles/metafiles/.vscodeignore
dotfiles/metafiles/CHANGELOG.md
dotfiles/metafiles/MANIFEST.in
dotfiles/metafiles/Makefile
dotfiles/metafiles/README.md
dotfiles/metafiles/altREADME.md
dotfiles/metafiles/mkdocs.yml
dotfiles/metafiles/pyproject.toml
dotfiles/metafiles/setup.py
dotfiles/metafiles/tox.ini
dotfiles/metafiles/workflow.yml
ap_dotfiles-0.1.0.dist-info/METADATA
ap_dotfiles-0.1.0.dist-info/WHEEL
ap_dotfiles-0.1.0.dist-info/entry_points.txt
ap_dotfiles-0.1.0.dist-info/top_level.txt
ap_dotfiles-0.1.0.dist-info/RECORD
