Metadata-Version: 2.1
Name: ap-dotfiles
Version: 0.1.0
Summary: Default meta docs for new projects
Home-page: http://github.com/alexpdev/dotfiles
Author: alexpdev
Author-email: alexpdev@protonmail.com
License: GNU GPL v3
Project-URL: Source Code, https://github.com/alexpdev/dotfiles
Keywords: Meta,Docs
Platform: UNKNOWN
Classifier: Development Status :: 3 - Alpha
